genaudit/__init__.py
genaudit/get_example.py
genaudit/launch.py
genaudit/qa_models.py
genaudit/examples/saved/Ex1_discharge_summary.json
genaudit/examples/saved/Ex2_clinical_transcript.json
genaudit/factcheckers/__init__.py
genaudit/factcheckers/base.py
genaudit/factcheckers/hf_predictor.py
genaudit/factcheckers/utils.py
genaudit/webroot/example.js
genaudit/webroot/index.html
genaudit/webroot/logo.png
genaudit/webroot/style.css
genaudit/webroot/resource_files/active-line.js
genaudit/webroot/resource_files/angular-1.6.1.min.js
genaudit/webroot/resource_files/angular-animate-1.6.1.min.js
genaudit/webroot/resource_files/angular-sanitize-1.6.1.js
genaudit/webroot/resource_files/annotatescrollbar.js
genaudit/webroot/resource_files/bootstrap-4.5.0.min.css
genaudit/webroot/resource_files/bootstrap-4.5.2.min.js
genaudit/webroot/resource_files/codemirror.css
genaudit/webroot/resource_files/codemirror.js
genaudit/webroot/resource_files/dialog.css
genaudit/webroot/resource_files/dialog.js
genaudit/webroot/resource_files/docs.css
genaudit/webroot/resource_files/font-awesome-all-6.4.2.min.css
genaudit/webroot/resource_files/javascript-hint.js
genaudit/webroot/resource_files/javascript.js
genaudit/webroot/resource_files/jquery-3.3.1.min.js
genaudit/webroot/resource_files/jump-to-line.js
genaudit/webroot/resource_files/markdown.js
genaudit/webroot/resource_files/match-highlighter.js
genaudit/webroot/resource_files/matchesonscrollbar.css
genaudit/webroot/resource_files/matchesonscrollbar.js
genaudit/webroot/resource_files/popper.min.js
genaudit/webroot/resource_files/search.js
genaudit/webroot/resource_files/searchcursor.js
genaudit/webroot/resource_files/show-hint.css
genaudit/webroot/resource_files/show-hint.js
genaudit/webroot/resource_files/ui-bootstrap-tpls-2.5.0.js
genaudit-0.1.1.dist-info/METADATA
genaudit-0.1.1.dist-info/WHEEL
genaudit-0.1.1.dist-info/licenses/LICENSE
genaudit-0.1.1.dist-info/RECORD
