Metadata-Version: 2.4
Name: genaudit
Version: 0.1.1
Summary: GenAudit is a tool to fact-check text, especially AI-generated text against reference documents.
Project-URL: Homepage, http://genaudit.org
Project-URL: Repository, https://github.com/kukrishna/genaudit.git
Author-email: Kundan Krishna <kundan.krishna99@gmail.com>
Maintainer-email: Kundan Krishna <kundan.krishna99@gmail.com>
License-Expression: Apache-2.0
License-File: LICENSE
Keywords: evidence,factchecking,llm,nli,nlp
Classifier: Programming Language :: Python
Requires-Python: <3.10,>=3.9
Requires-Dist: accelerate==0.32.1
Requires-Dist: bitsandbytes>=0.39.1
Requires-Dist: bottle==0.12.23
Requires-Dist: einops>=0.6.1
Requires-Dist: huggingface-hub==0.24.7
Requires-Dist: jsonlines
Requires-Dist: nltk
Requires-Dist: openai
Requires-Dist: paste
Requires-Dist: peft==0.5.0
Requires-Dist: sentencepiece
Requires-Dist: spacy
Requires-Dist: tenacity
Requires-Dist: tiktoken
Requires-Dist: transformers==4.38.1
